{"version":1,"resource":"file:///mnt/windows1/Project/Employee/sandbox.js","entries":[{"id":"62Hr.js","timestamp":1677370681985},{"id":"qsF3.js","timestamp":1677370788666},{"id":"seIB.js","timestamp":1677370857782},{"id":"NKsG.js","timestamp":1677370960156},{"id":"iKbA.js","timestamp":1677371060740},{"id":"zhLR.js","timestamp":1677371549966},{"id":"wxsE.js","timestamp":1677371590486},{"id":"ndUn.js","timestamp":1677371613182},{"id":"zYBV.js","timestamp":1677371638178},{"id":"9uPp.js","timestamp":1677371677729},{"id":"sbEn.js","timestamp":1677371697214},{"id":"liTq.js","timestamp":1677371807179},{"id":"exsw.js","timestamp":1677371817185},{"id":"C1R8.js","timestamp":1677371839046},{"id":"PVpu.js","timestamp":1677371891089},{"id":"1r2w.js","timestamp":1677371909663},{"id":"Odp4.js","timestamp":1677371927401},{"id":"9wrA.js","timestamp":1677371945845},{"id":"s8UW.js","timestamp":1677371979753},{"id":"4Xiw.js","timestamp":1677372058073},{"id":"BXhI.js","timestamp":1677372366308},{"id":"SvwV.js","timestamp":1677372381533},{"id":"9G3t.js","timestamp":1677372417549},{"id":"2J85.js","timestamp":1677372515444},{"id":"Hflr.js","timestamp":1677372642780},{"id":"bMie.js","timestamp":1677372728591},{"id":"l3Cl.js","timestamp":1677372746643},{"id":"Cmbr.js","timestamp":1677372789137},{"id":"n2G0.js","timestamp":1677372822923},{"id":"fMhW.js","timestamp":1677373126175},{"id":"GOlv.js","timestamp":1677373157055},{"id":"SYLB.js","timestamp":1677373173885},{"id":"Oguc.js","timestamp":1677373199607},{"id":"B8DA.js","timestamp":1677373212250},{"id":"BQ3a.js","timestamp":1677373244332},{"id":"tlpD.js","timestamp":1677373263106},{"id":"qYdZ.js","timestamp":1677373317540},{"id":"FcEQ.js","timestamp":1677373335225},{"id":"cX1S.js","timestamp":1677373539831},{"id":"8IFv.js","timestamp":1677373677275},{"id":"VQHn.js","timestamp":1677374049684},{"id":"n2gF.js","timestamp":1677374068424},{"id":"FMpv.js","timestamp":1677374161389},{"id":"U0oG.js","timestamp":1677374195853},{"id":"leM2.js","timestamp":1677374294182},{"id":"HU3h.js","timestamp":1677374407791},{"id":"9OuX.js","timestamp":1677374503725},{"id":"u8l4.js","timestamp":1677374603209},{"id":"lIWd.js","timestamp":1677376176531},{"id":"RyU6.js","timestamp":1677376244065}]}